agent/__init__.py
agent/agent.py
agent/metrics_utils.py
server/__init__.py
server/config_loader.py
server/http_bridge.py
server/server.py
test_monitoring_system_server_report_2-0.1.2.dist-info/METADATA
test_monitoring_system_server_report_2-0.1.2.dist-info/WHEEL
test_monitoring_system_server_report_2-0.1.2.dist-info/entry_points.txt
test_monitoring_system_server_report_2-0.1.2.dist-info/top_level.txt
test_monitoring_system_server_report_2-0.1.2.dist-info/RECORD
